dataset/avatars.py
dataset/collect_brands_data.py
dataset/constants.py
nike_detector/nike_detector/service/evaluation_pipeline_params.py
nike_detector/nike_detector/service/service.py
nike_detector/nike_detector/service/train.py
nike_detector/nike_detector/service/configs/base_config.yaml
nike_detector-0.0.18.dist-info/METADATA
nike_detector-0.0.18.dist-info/WHEEL
nike_detector-0.0.18.dist-info/top_level.txt
nike_detector-0.0.18.dist-info/RECORD
