Metadata-Version: 2.1
Name: nike-detector
Version: 0.0.18
Summary: Package for Nike logos detection
Author-email: korotkov <ma-korotkov@yandex.ru>
Classifier: Programming Language :: Python :: 3
Classifier: Operating System :: OS Independent
Requires-Python: >=3.7
Requires-Dist: torch ==1.13.1
Requires-Dist: ultralytics ==8.0.164
Requires-Dist: Pillow ==9.2.0
Requires-Dist: gdown ==4.7.1
Requires-Dist: marshmallow-dataclass ==8.5.8
Requires-Dist: dataclasses ==0.6
